{
  "HALProvider": {
    "Other Devices": {
      "Talon FX[15]": {
        "header": {
          "open": true
        }
      },
      "Talon FX[15]/Integrated Sensor": {
        "header": {
          "open": true
        }
      },
      "Talon FX[19]": {
        "header": {
          "open": true
        }
      },
      "Talon FX[1]": {
        "header": {
          "open": true
        }
      },
      "Talon FX[1]/Integrated Sensor": {
        "header": {
          "open": true
        }
      }
    }
  },
  "NTProvider": {
    "types": {
      "/FMSInfo": "FMSInfo",
      "/LiveWindow/Ungrouped/Scheduler": "Scheduler",
      "/Shuffleboard/Shooter Tuning/Flywheel Motor": "Motor Controller",
      "/Shuffleboard/Shooter Tuning/Flywheel Motor Control/Flywheel Motor": "Motor Controller",
      "/Shuffleboard/Shooter Tuning/Flywheel Motor Control/PID Selection": "String Chooser",
      "/Shuffleboard/Shooter Tuning/Onboard PID/TalonFX Onboard PID": "PIDController",
      "/Shuffleboard/Shooter Tuning/PID Control/Enable Motor": "Command",
      "/Shuffleboard/Shooter Tuning/PID Control/PID Selection": "String Chooser",
      "/Shuffleboard/Shooter Tuning/PID Control/TalonFX Onboard PID": "PIDController",
      "/Shuffleboard/Shooter Tuning/PID Selection": "String Chooser",
      "/Shuffleboard/Shooter Tuning/Software Feed Forward/Software PID": "PIDController",
      "/Shuffleboard/Shooter Tuning/TalonFX": "Motor Controller",
      "/Shuffleboard/Shooter Tuning/TalonFX Onboard PID": "PIDController",
      "/Shuffleboard/Shooter Tuning/TalonFX Software PID": "PIDController",
      "/Shuffleboard/TalonFXWidget/Shooter Motor/Control Mode": "String Chooser",
      "/Shuffleboard/TalonFXWidget/Shooter Motor/Motor Percent Output": "Motor Controller",
      "/Shuffleboard/TalonFXWidget/Shooter Motor/Motor Status/Control Mode": "String Chooser",
      "/Shuffleboard/TalonFXWidget/Shooter Motor/Onboard PID Settings": "PIDController",
      "/Shuffleboard/TalonFXWidget/Shooter Motor/PID Settings": "PIDController"
    }
  },
  "NetworkTables": {
    "Shuffleboard": {
      ".metadata": {
        "Shooter Tuning": {
          "Software PID Settings": {
            "Motor RPM": {
              "open": true
            },
            "Properties": {
              "open": true
            },
            "Software FF Output(V)": {
              "open": true
            },
            "Software FF kA": {
              "open": true
            },
            "Software FF kS": {
              "open": true
            },
            "Software FF kV": {
              "open": true
            },
            "Software PID Output(V)": {
              "open": true
            }
          },
          "open": true
        },
        "TalonFXWidget": {
          "open": true
        },
        "open": true
      },
      "Shooter Tuning": {
        "TalonFX": {
          "open": true
        },
        "TalonFX Onboard PID": {
          "open": true
        },
        "TalonFX Software PID": {
          "open": true
        }
      },
      "open": true
    }
  }
}
